ShoubashouJiaonizuoYigeCYuyanBianyiqi/README.md
ShoubashouJiaonizuoYigeCYuyanBianyiqi/__init__.py
ShoubashouJiaonizuoYigeCYuyanBianyiqi/__main__.py
ShoubashouJiaonizuoYigeCYuyanBianyiqi/file.epub
ShoubashouJiaonizuoYigeCYuyanBianyiqi/index.html
ShoubashouJiaonizuoYigeCYuyanBianyiqi/css/__init__.py
ShoubashouJiaonizuoYigeCYuyanBianyiqi/css/annotations.css
ShoubashouJiaonizuoYigeCYuyanBianyiqi/css/main.css
ShoubashouJiaonizuoYigeCYuyanBianyiqi/css/normalize.css
ShoubashouJiaonizuoYigeCYuyanBianyiqi/css/popup.css
ShoubashouJiaonizuoYigeCYuyanBianyiqi/font/__init__.py
ShoubashouJiaonizuoYigeCYuyanBianyiqi/font/fontello.eot
ShoubashouJiaonizuoYigeCYuyanBianyiqi/font/fontello.svg
ShoubashouJiaonizuoYigeCYuyanBianyiqi/font/fontello.ttf
ShoubashouJiaonizuoYigeCYuyanBianyiqi/font/fontello.woff
ShoubashouJiaonizuoYigeCYuyanBianyiqi/img/__init__.py
ShoubashouJiaonizuoYigeCYuyanBianyiqi/img/annotator-glyph-sprite.png
ShoubashouJiaonizuoYigeCYuyanBianyiqi/img/annotator-icon-sprite.png
ShoubashouJiaonizuoYigeCYuyanBianyiqi/img/apple-touch-icon.png
ShoubashouJiaonizuoYigeCYuyanBianyiqi/img/cancelfullscreen.png
ShoubashouJiaonizuoYigeCYuyanBianyiqi/img/close.png
ShoubashouJiaonizuoYigeCYuyanBianyiqi/img/fullscreen.png
ShoubashouJiaonizuoYigeCYuyanBianyiqi/img/loader.gif
ShoubashouJiaonizuoYigeCYuyanBianyiqi/img/menu-icon.png
ShoubashouJiaonizuoYigeCYuyanBianyiqi/img/save.png
ShoubashouJiaonizuoYigeCYuyanBianyiqi/img/saved.png
ShoubashouJiaonizuoYigeCYuyanBianyiqi/img/settings-s.png
ShoubashouJiaonizuoYigeCYuyanBianyiqi/img/settings.png
ShoubashouJiaonizuoYigeCYuyanBianyiqi/img/star.png
ShoubashouJiaonizuoYigeCYuyanBianyiqi/js/__init__.py
ShoubashouJiaonizuoYigeCYuyanBianyiqi/js/epub.js
ShoubashouJiaonizuoYigeCYuyanBianyiqi/js/epub.min.js
ShoubashouJiaonizuoYigeCYuyanBianyiqi/js/epub.min.map
ShoubashouJiaonizuoYigeCYuyanBianyiqi/js/hooks.min.js
ShoubashouJiaonizuoYigeCYuyanBianyiqi/js/hooks.min.map
ShoubashouJiaonizuoYigeCYuyanBianyiqi/js/reader.js
shoubashou_jiaonizuo_yige_c_yuyan_bianyiqi-2024.3.2.0.dist-info/METADATA
shoubashou_jiaonizuo_yige_c_yuyan_bianyiqi-2024.3.2.0.dist-info/WHEEL
shoubashou_jiaonizuo_yige_c_yuyan_bianyiqi-2024.3.2.0.dist-info/entry_points.txt
shoubashou_jiaonizuo_yige_c_yuyan_bianyiqi-2024.3.2.0.dist-info/top_level.txt
shoubashou_jiaonizuo_yige_c_yuyan_bianyiqi-2024.3.2.0.dist-info/RECORD
